mcp_rememberizer_vectordb/__init__.py
mcp_rememberizer_vectordb/server.py
mcp_rememberizer_vectordb/utils.py
mseep_mcp_rememberizer_vectordb-0.1.7.dist-info/licenses/LICENSE
mseep_mcp_rememberizer_vectordb-0.1.7.dist-info/METADATA
mseep_mcp_rememberizer_vectordb-0.1.7.dist-info/WHEEL
mseep_mcp_rememberizer_vectordb-0.1.7.dist-info/entry_points.txt
mseep_mcp_rememberizer_vectordb-0.1.7.dist-info/top_level.txt
mseep_mcp_rememberizer_vectordb-0.1.7.dist-info/RECORD
